qemu_affinity.py
qemu_affinity-1.0.0.dist-info/DESCRIPTION.rst
qemu_affinity-1.0.0.dist-info/METADATA
qemu_affinity-1.0.0.dist-info/RECORD
qemu_affinity-1.0.0.dist-info/WHEEL
qemu_affinity-1.0.0.dist-info/entry_points.txt
qemu_affinity-1.0.0.dist-info/metadata.json
qemu_affinity-1.0.0.dist-info/top_level.txt
