Metadata-Version: 2.0
Name: qemu-affinity
Version: 1.0.0
Summary: A tool to easily pin certain QEMU threads to select CPU cores.
Home-page: http://packages.python.org/an_example_pypi_project
Author: Adam Zegelin
Author-email: adam@zegelin.com
License: MIT
Keywords: qemu affinity
Platform: UNKNOWN
Classifier: Development Status :: 5 - Production/Stable
Classifier: Intended Audience :: System Administrators
Classifier: Topic :: Utilities
Classifier: Environment :: Console
Classifier: License :: OSI Approved :: MIT License
Classifier: Operating System :: POSIX :: Linux
Classifier: Programming Language :: Python :: 3
